{
  "openapi": "3.1.0",
  "info": {
    "title": "enterprise_ai_backend",
    "description": "Enterprise AI Reliability Platform - Backend API (full build)",
    "version": "0.3.0"
  },
  "paths": {
    "/health": {
      "get": {
        "tags": [
          "system"
        ],
        "summary": "Health",
        "operationId": "health_health_get",
        "responses": {
          "200": {
            "description": "Successful Response",
            "content": {
              "application/json": {
                "schema": {
                  "$ref": "#/components/schemas/HealthResponse"
                }
              }
            }
          }
        }
      }
    },
    "/auth/register": {
      "post": {
        "tags": [
          "auth"
        ],
        "summary": "Register",
        "operationId": "register_auth_register_post",
        "requestBody": {
          "content": {
            "application/json": {
              "schema": {
                "$ref": "#/components/schemas/UserRegister"
              }
            }
          },
          "required": true
        },
        "responses": {
          "201": {
            "description": "Successful Response",
            "content": {
              "application/json": {
                "schema": {
                  "$ref": "#/components/schemas/UserOut"
                }
              }
            }
          },
          "422": {
            "description": "Validation Error",
            "content": {
              "application/json": {
                "schema": {
                  "$ref": "#/components/schemas/HTTPValidationError"
                }
              }
            }
          }
        }
      }
    },
    "/auth/login": {
      "post": {
        "tags": [
          "auth"
        ],
        "summary": "Login",
        "operationId": "login_auth_login_post",
        "requestBody": {
          "content": {
            "application/json": {
              "schema": {
                "$ref": "#/components/schemas/UserLogin"
              }
            }
          },
          "required": true
        },
        "responses": {
          "200": {
            "description": "Successful Response",
            "content": {
              "application/json": {
                "schema": {
                  "$ref": "#/components/schemas/TokenOut"
                }
              }
            }
          },
          "422": {
            "description": "Validation Error",
            "content": {
              "application/json": {
                "schema": {
                  "$ref": "#/components/schemas/HTTPValidationError"
                }
              }
            }
          }
        }
      }
    },
    "/auth/me": {
      "get": {
        "tags": [
          "auth"
        ],
        "summary": "Me",
        "operationId": "me_auth_me_get",
        "responses": {
          "200": {
            "description": "Successful Response",
            "content": {
              "application/json": {
                "schema": {
                  "$ref": "#/components/schemas/UserOut"
                }
              }
            }
          }
        },
        "security": [
          {
            "OAuth2PasswordBearer": []
          }
        ]
      }
    },
    "/reliability/compute": {
      "post": {
        "tags": [
          "reliability"
        ],
        "summary": "Compute",
        "description": "MTBF/MTTR/mission-time \u2192 availability, reliability, failure rate.",
        "operationId": "compute_reliability_compute_post",
        "requestBody": {
          "content": {
            "application/json": {
              "schema": {
                "$ref": "#/components/schemas/ReliabilityInput"
              }
            }
          },
          "required": true
        },
        "responses": {
          "200": {
            "description": "Successful Response",
            "content": {
              "application/json": {
                "schema": {
                  "$ref": "#/components/schemas/ReliabilityOutput"
                }
              }
            }
          },
          "422": {
            "description": "Validation Error",
            "content": {
              "application/json": {
                "schema": {
                  "$ref": "#/components/schemas/HTTPValidationError"
                }
              }
            }
          }
        }
      }
    },
    "/reliability/history": {
      "get": {
        "tags": [
          "reliability"
        ],
        "summary": "History",
        "description": "Recent reliability computations, newest first.",
        "operationId": "history_reliability_history_get",
        "parameters": [
          {
            "name": "limit",
            "in": "query",
            "required": false,
            "schema": {
              "type": "integer",
              "default": 50,
              "title": "Limit"
            }
          }
        ],
        "responses": {
          "200": {
            "description": "Successful Response",
            "content": {
              "application/json": {
                "schema": {
                  "type": "array",
                  "items": {
                    "$ref": "#/components/schemas/ReliabilityOutput"
                  },
                  "title": "Response History Reliability History Get"
                }
              }
            }
          },
          "422": {
            "description": "Validation Error",
            "content": {
              "application/json": {
                "schema": {
                  "$ref": "#/components/schemas/HTTPValidationError"
                }
              }
            }
          }
        }
      }
    },
    "/reliability/score": {
      "post": {
        "tags": [
          "reliability"
        ],
        "summary": "Score",
        "description": "Weighted composite reliability score across multiple signals.\n\nEach component has a ``value`` in [0, 1] and a ``weight``. Components\nare combined into a single 0-100 composite score, placed into a tier\n(LOW/MEDIUM/HIGH), and optionally rolled up per NIST AI RMF function.\n\nEach call is persisted (Sprint 2 E2-S3) so\n``GET /reliability/score/history`` can trend it over time.",
        "operationId": "score_reliability_score_post",
        "requestBody": {
          "content": {
            "application/json": {
              "schema": {
                "$ref": "#/components/schemas/ReliabilityScoreInput"
              }
            }
          },
          "required": true
        },
        "responses": {
          "200": {
            "description": "Successful Response",
            "content": {
              "application/json": {
                "schema": {
                  "$ref": "#/components/schemas/ReliabilityScoreOutput"
                }
              }
            }
          },
          "422": {
            "description": "Validation Error",
            "content": {
              "application/json": {
                "schema": {
                  "$ref": "#/components/schemas/HTTPValidationError"
                }
              }
            }
          }
        }
      }
    },
    "/reliability/score/explain": {
      "post": {
        "tags": [
          "reliability"
        ],
        "summary": "Score Explain",
        "description": "Composite reliability score + per-component explanation.\n\nExtends ``POST /reliability/score`` with an ``explanation`` object that\nidentifies:\n\n* ``top_driver`` and ``top_gap`` components,\n* per-component contributions (absolute and percent of the composite),\n* distance to adjacent tier boundaries (``tier_gap``),\n* weakest / strongest NIST AI RMF function, and\n* a one-sentence plain-English recommendation.\n\nAlso persists the underlying score record (Sprint 2 E2-S3).",
        "operationId": "score_explain_reliability_score_explain_post",
        "requestBody": {
          "content": {
            "application/json": {
              "schema": {
                "$ref": "#/components/schemas/ReliabilityScoreInput"
              }
            }
          },
          "required": true
        },
        "responses": {
          "200": {
            "description": "Successful Response",
            "content": {
              "application/json": {
                "schema": {
                  "$ref": "#/components/schemas/ReliabilityScoreWithExplanation"
                }
              }
            }
          },
          "422": {
            "description": "Validation Error",
            "content": {
              "application/json": {
                "schema": {
                  "$ref": "#/components/schemas/HTTPValidationError"
                }
              }
            }
          }
        }
      }
    },
    "/reliability/score/history": {
      "get": {
        "tags": [
          "reliability"
        ],
        "summary": "Score History",
        "description": "Return recent composite scores (newest first) plus trend stats.\n\nPopulated automatically by every ``POST /reliability/score`` and\n``POST /reliability/score/explain`` call. The ``stats`` object\nincludes rolling average, min/max, a simple improving / degrading /\nstable trend classification, and any tier transitions.",
        "operationId": "score_history_reliability_score_history_get",
        "parameters": [
          {
            "name": "system_name",
            "in": "query",
            "required": false,
            "schema": {
              "anyOf": [
                {
                  "type": "string"
                },
                {
                  "type": "null"
                }
              ],
              "description": "Filter by system name (exact match). Omit for all systems.",
              "title": "System Name"
            },
            "description": "Filter by system name (exact match). Omit for all systems."
          },
          {
            "name": "limit",
            "in": "query",
            "required": false,
            "schema": {
              "type": "integer",
              "maximum": 500,
              "minimum": 1,
              "default": 50,
              "title": "Limit"
            }
          }
        ],
        "responses": {
          "200": {
            "description": "Successful Response",
            "content": {
              "application/json": {
                "schema": {
                  "$ref": "#/components/schemas/ReliabilityScoreHistoryOut"
                }
              }
            }
          },
          "422": {
            "description": "Validation Error",
            "content": {
              "application/json": {
                "schema": {
                  "$ref": "#/components/schemas/HTTPValidationError"
                }
              }
            }
          }
        }
      }
    },
    "/policy/evaluate": {
      "post": {
        "tags": [
          "policy"
        ],
        "summary": "Evaluate",
        "description": "Evaluate the policy gate on a reliability score input.\n\nThe request body carries the same shape as ``POST /reliability/score``\n(a ``system_name`` + list of ``ReliabilityScoreComponent``) plus an\noptional ``thresholds`` override. The response is an ``allow`` /\n``warn`` / ``block`` decision with a list of rationale ``reasons``,\nthe applied thresholds (echoed), and the resolved composite score\nand tier.",
        "operationId": "evaluate_policy_evaluate_post",
        "requestBody": {
          "content": {
            "application/json": {
              "schema": {
                "$ref": "#/components/schemas/PolicyGateInput"
              }
            }
          },
          "required": true
        },
        "responses": {
          "200": {
            "description": "Successful Response",
            "content": {
              "application/json": {
                "schema": {
                  "$ref": "#/components/schemas/PolicyGateDecision"
                }
              }
            }
          },
          "422": {
            "description": "Validation Error",
            "content": {
              "application/json": {
                "schema": {
                  "$ref": "#/components/schemas/HTTPValidationError"
                }
              }
            }
          }
        }
      }
    },
    "/assessments": {
      "post": {
        "tags": [
          "assessments"
        ],
        "summary": "Create",
        "operationId": "create_assessments_post",
        "security": [
          {
            "OAuth2PasswordBearer": []
          }
        ],
        "requestBody": {
          "required": true,
          "content": {
            "application/json": {
              "schema": {
                "$ref": "#/components/schemas/AssessmentInput"
              }
            }
          }
        },
        "responses": {
          "201": {
            "description": "Successful Response",
            "content": {
              "application/json": {
                "schema": {
                  "$ref": "#/components/schemas/AssessmentOutput"
                }
              }
            }
          },
          "422": {
            "description": "Validation Error",
            "content": {
              "application/json": {
                "schema": {
                  "$ref": "#/components/schemas/HTTPValidationError"
                }
              }
            }
          }
        }
      },
      "get": {
        "tags": [
          "assessments"
        ],
        "summary": "List All",
        "operationId": "list_all_assessments_get",
        "security": [
          {
            "OAuth2PasswordBearer": []
          }
        ],
        "parameters": [
          {
            "name": "limit",
            "in": "query",
            "required": false,
            "schema": {
              "type": "integer",
              "default": 50,
              "title": "Limit"
            }
          }
        ],
        "responses": {
          "200": {
            "description": "Successful Response",
            "content": {
              "application/json": {
                "schema": {
                  "type": "array",
                  "items": {
                    "$ref": "#/components/schemas/AssessmentOutput"
                  },
                  "title": "Response List All Assessments Get"
                }
              }
            }
          },
          "422": {
            "description": "Validation Error",
            "content": {
              "application/json": {
                "schema": {
                  "$ref": "#/components/schemas/HTTPValidationError"
                }
              }
            }
          }
        }
      }
    },
    "/assessments/{assessment_id}": {
      "get": {
        "tags": [
          "assessments"
        ],
        "summary": "Get One",
        "operationId": "get_one_assessments__assessment_id__get",
        "security": [
          {
            "OAuth2PasswordBearer": []
          }
        ],
        "parameters": [
          {
            "name": "assessment_id",
            "in": "path",
            "required": true,
            "schema": {
              "type": "integer",
              "title": "Assessment Id"
            }
          }
        ],
        "responses": {
          "200": {
            "description": "Successful Response",
            "content": {
              "application/json": {
                "schema": {
                  "$ref": "#/components/schemas/AssessmentOutput"
                }
              }
            }
          },
          "422": {
            "description": "Validation Error",
            "content": {
              "application/json": {
                "schema": {
                  "$ref": "#/components/schemas/HTTPValidationError"
                }
              }
            }
          }
        }
      }
    },
    "/ai/anomaly-detect": {
      "post": {
        "tags": [
          "ai"
        ],
        "summary": "Detect",
        "operationId": "detect_ai_anomaly_detect_post",
        "requestBody": {
          "content": {
            "application/json": {
              "schema": {
                "$ref": "#/components/schemas/AnomalyInput"
              }
            }
          },
          "required": true
        },
        "responses": {
          "200": {
            "description": "Successful Response",
            "content": {
              "application/json": {
                "schema": {
                  "$ref": "#/components/schemas/AnomalyOutput"
                }
              }
            }
          },
          "422": {
            "description": "Validation Error",
            "content": {
              "application/json": {
                "schema": {
                  "$ref": "#/components/schemas/HTTPValidationError"
                }
              }
            }
          }
        },
        "security": [
          {
            "OAuth2PasswordBearer": []
          }
        ]
      }
    },
    "/ai/anomaly-detect/from-history": {
      "get": {
        "tags": [
          "ai"
        ],
        "summary": "Detect From History",
        "operationId": "detect_from_history_ai_anomaly_detect_from_history_get",
        "security": [
          {
            "OAuth2PasswordBearer": []
          }
        ],
        "parameters": [
          {
            "name": "contamination",
            "in": "query",
            "required": false,
            "schema": {
              "type": "number",
              "default": 0.1,
              "title": "Contamination"
            }
          }
        ],
        "responses": {
          "200": {
            "description": "Successful Response",
            "content": {
              "application/json": {
                "schema": {
                  "$ref": "#/components/schemas/AnomalyOutput"
                }
              }
            }
          },
          "422": {
            "description": "Validation Error",
            "content": {
              "application/json": {
                "schema": {
                  "$ref": "#/components/schemas/HTTPValidationError"
                }
              }
            }
          }
        }
      }
    },
    "/hash/sha256": {
      "post": {
        "tags": [
          "utility"
        ],
        "summary": "Sha256 Endpoint",
        "operationId": "sha256_endpoint_hash_sha256_post",
        "requestBody": {
          "content": {
            "application/json": {
              "schema": {
                "$ref": "#/components/schemas/HashInput"
              }
            }
          },
          "required": true
        },
        "responses": {
          "200": {
            "description": "Successful Response",
            "content": {
              "application/json": {
                "schema": {
                  "$ref": "#/components/schemas/HashOutput"
                }
              }
            }
          },
          "422": {
            "description": "Validation Error",
            "content": {
              "application/json": {
                "schema": {
                  "$ref": "#/components/schemas/HTTPValidationError"
                }
              }
            }
          }
        }
      }
    },
    "/info/epics": {
      "get": {
        "tags": [
          "system"
        ],
        "summary": "List Epics",
        "description": "Return the product backlog epics and their status.",
        "operationId": "list_epics_info_epics_get",
        "responses": {
          "200": {
            "description": "Successful Response",
            "content": {
              "application/json": {
                "schema": {
                  "items": {
                    "$ref": "#/components/schemas/Epic"
                  },
                  "type": "array",
                  "title": "Response List Epics Info Epics Get"
                }
              }
            }
          }
        }
      }
    },
    "/info/sprint": {
      "get": {
        "tags": [
          "system"
        ],
        "summary": "Current Sprint",
        "description": "Return the current sprint summary.",
        "operationId": "current_sprint_info_sprint_get",
        "responses": {
          "200": {
            "description": "Successful Response",
            "content": {
              "application/json": {
                "schema": {
                  "$ref": "#/components/schemas/SprintSummary"
                }
              }
            }
          }
        }
      }
    },
    "/": {
      "get": {
        "summary": "Root",
        "operationId": "root__get",
        "responses": {
          "200": {
            "description": "Successful Response",
            "content": {
              "application/json": {
                "schema": {}
              }
            }
          }
        }
      }
    }
  },
  "components": {
    "schemas": {
      "AnomalyInput": {
        "properties": {
          "records": {
            "items": {
              "items": {
                "type": "number"
              },
              "type": "array"
            },
            "type": "array",
            "minItems": 2,
            "title": "Records",
            "description": "List of feature vectors (2+ records required)"
          },
          "contamination": {
            "type": "number",
            "exclusiveMaximum": 0.5,
            "exclusiveMinimum": 0.0,
            "title": "Contamination",
            "default": 0.1
          }
        },
        "type": "object",
        "required": [
          "records"
        ],
        "title": "AnomalyInput"
      },
      "AnomalyOutput": {
        "properties": {
          "n_trained_on": {
            "type": "integer",
            "title": "N Trained On"
          },
          "n_scored": {
            "type": "integer",
            "title": "N Scored"
          },
          "predictions": {
            "items": {
              "type": "integer"
            },
            "type": "array",
            "title": "Predictions"
          },
          "scores": {
            "items": {
              "type": "number"
            },
            "type": "array",
            "title": "Scores"
          },
          "anomaly_count": {
            "type": "integer",
            "title": "Anomaly Count"
          },
          "model": {
            "type": "string",
            "title": "Model"
          },
          "record_ids": {
            "anyOf": [
              {
                "items": {
                  "type": "integer"
                },
                "type": "array"
              },
              {
                "type": "null"
              }
            ],
            "title": "Record Ids"
          }
        },
        "type": "object",
        "required": [
          "n_trained_on",
          "n_scored",
          "predictions",
          "scores",
          "anomaly_count",
          "model"
        ],
        "title": "AnomalyOutput"
      },
      "AssessmentInput": {
        "properties": {
          "system_name": {
            "type": "string",
            "maxLength": 200,
            "minLength": 1,
            "title": "System Name"
          },
          "owner": {
            "type": "string",
            "maxLength": 200,
            "minLength": 1,
            "title": "Owner"
          },
          "govern_score": {
            "type": "integer",
            "maximum": 100.0,
            "minimum": 0.0,
            "title": "Govern Score"
          },
          "map_score": {
            "type": "integer",
            "maximum": 100.0,
            "minimum": 0.0,
            "title": "Map Score"
          },
          "measure_score": {
            "type": "integer",
            "maximum": 100.0,
            "minimum": 0.0,
            "title": "Measure Score"
          },
          "manage_score": {
            "type": "integer",
            "maximum": 100.0,
            "minimum": 0.0,
            "title": "Manage Score"
          },
          "notes": {
            "anyOf": [
              {
                "type": "string"
              },
              {
                "type": "null"
              }
            ],
            "title": "Notes"
          }
        },
        "type": "object",
        "required": [
          "system_name",
          "owner",
          "govern_score",
          "map_score",
          "measure_score",
          "manage_score"
        ],
        "title": "AssessmentInput"
      },
      "AssessmentOutput": {
        "properties": {
          "id": {
            "type": "integer",
            "title": "Id"
          },
          "system_name": {
            "type": "string",
            "title": "System Name"
          },
          "owner": {
            "type": "string",
            "title": "Owner"
          },
          "govern_score": {
            "type": "integer",
            "title": "Govern Score"
          },
          "map_score": {
            "type": "integer",
            "title": "Map Score"
          },
          "measure_score": {
            "type": "integer",
            "title": "Measure Score"
          },
          "manage_score": {
            "type": "integer",
            "title": "Manage Score"
          },
          "overall_score": {
            "type": "number",
            "title": "Overall Score"
          },
          "risk_tier": {
            "type": "string",
            "title": "Risk Tier"
          },
          "notes": {
            "anyOf": [
              {
                "type": "string"
              },
              {
                "type": "null"
              }
            ],
            "title": "Notes"
          },
          "created_at": {
            "type": "string",
            "format": "date-time",
            "title": "Created At"
          }
        },
        "type": "object",
        "required": [
          "id",
          "system_name",
          "owner",
          "govern_score",
          "map_score",
          "measure_score",
          "manage_score",
          "overall_score",
          "risk_tier",
          "created_at"
        ],
        "title": "AssessmentOutput"
      },
      "Epic": {
        "properties": {
          "id": {
            "type": "string",
            "title": "Id"
          },
          "title": {
            "type": "string",
            "title": "Title"
          },
          "status": {
            "type": "string",
            "title": "Status"
          },
          "sprint": {
            "type": "integer",
            "title": "Sprint"
          }
        },
        "type": "object",
        "required": [
          "id",
          "title",
          "status",
          "sprint"
        ],
        "title": "Epic",
        "description": "A product backlog epic and its current delivery status."
      },
      "HTTPValidationError": {
        "properties": {
          "detail": {
            "items": {
              "$ref": "#/components/schemas/ValidationError"
            },
            "type": "array",
            "title": "Detail"
          }
        },
        "type": "object",
        "title": "HTTPValidationError"
      },
      "HashInput": {
        "properties": {
          "text": {
            "type": "string",
            "title": "Text"
          }
        },
        "type": "object",
        "required": [
          "text"
        ],
        "title": "HashInput"
      },
      "HashOutput": {
        "properties": {
          "text": {
            "type": "string",
            "title": "Text"
          },
          "sha256": {
            "type": "string",
            "title": "Sha256"
          },
          "length": {
            "type": "integer",
            "title": "Length"
          }
        },
        "type": "object",
        "required": [
          "text",
          "sha256",
          "length"
        ],
        "title": "HashOutput"
      },
      "HealthResponse": {
        "properties": {
          "status": {
            "type": "string",
            "title": "Status"
          },
          "app_name": {
            "type": "string",
            "title": "App Name"
          },
          "app_env": {
            "type": "string",
            "title": "App Env"
          },
          "app_version": {
            "type": "string",
            "title": "App Version"
          },
          "python_version": {
            "type": "string",
            "title": "Python Version"
          },
          "platform": {
            "type": "string",
            "title": "Platform"
          },
          "uptime_seconds": {
            "type": "number",
            "title": "Uptime Seconds"
          },
          "server_time_utc": {
            "type": "string",
            "title": "Server Time Utc"
          },
          "database": {
            "type": "string",
            "title": "Database"
          }
        },
        "type": "object",
        "required": [
          "status",
          "app_name",
          "app_env",
          "app_version",
          "python_version",
          "platform",
          "uptime_seconds",
          "server_time_utc",
          "database"
        ],
        "title": "HealthResponse"
      },
      "NISTBreakdown": {
        "properties": {
          "govern": {
            "anyOf": [
              {
                "type": "number"
              },
              {
                "type": "null"
              }
            ],
            "title": "Govern"
          },
          "map": {
            "anyOf": [
              {
                "type": "number"
              },
              {
                "type": "null"
              }
            ],
            "title": "Map"
          },
          "measure": {
            "anyOf": [
              {
                "type": "number"
              },
              {
                "type": "null"
              }
            ],
            "title": "Measure"
          },
          "manage": {
            "anyOf": [
              {
                "type": "number"
              },
              {
                "type": "null"
              }
            ],
            "title": "Manage"
          }
        },
        "type": "object",
        "title": "NISTBreakdown",
        "description": "Per-function weighted-average score, 0-100. None if no components\nin the request were tagged for that function."
      },
      "NISTFunction": {
        "type": "string",
        "enum": [
          "govern",
          "map",
          "measure",
          "manage"
        ],
        "title": "NISTFunction",
        "description": "NIST AI RMF 1.0 functions."
      },
      "PolicyDecision": {
        "type": "string",
        "enum": [
          "allow",
          "warn",
          "block"
        ],
        "title": "PolicyDecision",
        "description": "Overall gate outcome."
      },
      "PolicyGateDecision": {
        "properties": {
          "system_name": {
            "type": "string",
            "title": "System Name"
          },
          "decision": {
            "$ref": "#/components/schemas/PolicyDecision"
          },
          "composite_score": {
            "type": "number",
            "title": "Composite Score"
          },
          "tier": {
            "type": "string",
            "title": "Tier"
          },
          "reasons": {
            "items": {
              "$ref": "#/components/schemas/PolicyReason"
            },
            "type": "array",
            "title": "Reasons",
            "description": "All rules that fired, worst severity first."
          },
          "thresholds_applied": {
            "$ref": "#/components/schemas/PolicyThresholds"
          },
          "evaluated_at": {
            "type": "string",
            "format": "date-time",
            "title": "Evaluated At"
          }
        },
        "type": "object",
        "required": [
          "system_name",
          "decision",
          "composite_score",
          "tier",
          "reasons",
          "thresholds_applied",
          "evaluated_at"
        ],
        "title": "PolicyGateDecision",
        "description": "Response body for POST /policy/evaluate."
      },
      "PolicyGateInput": {
        "properties": {
          "score_input": {
            "$ref": "#/components/schemas/ReliabilityScoreInput"
          },
          "thresholds": {
            "anyOf": [
              {
                "$ref": "#/components/schemas/PolicyThresholds"
              },
              {
                "type": "null"
              }
            ],
            "description": "Override the default thresholds; omit to use defaults."
          }
        },
        "type": "object",
        "required": [
          "score_input"
        ],
        "title": "PolicyGateInput",
        "description": "Request body for POST /policy/evaluate."
      },
      "PolicyReason": {
        "properties": {
          "code": {
            "type": "string",
            "title": "Code",
            "description": "Short stable identifier for the rule."
          },
          "message": {
            "type": "string",
            "title": "Message",
            "description": "Plain-English explanation."
          },
          "severity": {
            "$ref": "#/components/schemas/PolicySeverity"
          }
        },
        "type": "object",
        "required": [
          "code",
          "message",
          "severity"
        ],
        "title": "PolicyReason",
        "description": "One machine-readable + human-readable rationale for the decision."
      },
      "PolicySeverity": {
        "type": "string",
        "enum": [
          "info",
          "warn",
          "block"
        ],
        "title": "PolicySeverity",
        "description": "Severity classification for a single policy reason."
      },
      "PolicyThresholds": {
        "properties": {
          "allow_min_composite": {
            "type": "number",
            "maximum": 100.0,
            "minimum": 0.0,
            "title": "Allow Min Composite",
            "description": "Composite score >= this value maps to 'allow'.",
            "default": 80.0
          },
          "warn_min_composite": {
            "type": "number",
            "maximum": 100.0,
            "minimum": 0.0,
            "title": "Warn Min Composite",
            "description": "Composite score >= this (and < allow threshold) maps to 'warn'.",
            "default": 60.0
          },
          "min_nist_function_score": {
            "type": "number",
            "maximum": 100.0,
            "minimum": 0.0,
            "title": "Min Nist Function Score",
            "description": "Per-function score floor; any tagged NIST function below this value forces 'block'.",
            "default": 40.0
          }
        },
        "type": "object",
        "title": "PolicyThresholds",
        "description": "Configurable thresholds controlling the gate outcome.\n\n``allow_min_composite`` and ``warn_min_composite`` partition the\ncomposite score into allow / warn / block bands; ``min_nist_function_score``\nis a hard floor -- any per-NIST-function breakdown below it forces\n``block`` regardless of composite."
      },
      "ReliabilityInput": {
        "properties": {
          "mtbf_hours": {
            "type": "number",
            "exclusiveMinimum": 0.0,
            "title": "Mtbf Hours"
          },
          "mttr_hours": {
            "type": "number",
            "exclusiveMinimum": 0.0,
            "title": "Mttr Hours"
          },
          "mission_time_hours": {
            "type": "number",
            "exclusiveMinimum": 0.0,
            "title": "Mission Time Hours"
          }
        },
        "type": "object",
        "required": [
          "mtbf_hours",
          "mttr_hours",
          "mission_time_hours"
        ],
        "title": "ReliabilityInput"
      },
      "ReliabilityOutput": {
        "properties": {
          "id": {
            "anyOf": [
              {
                "type": "integer"
              },
              {
                "type": "null"
              }
            ],
            "title": "Id"
          },
          "mtbf_hours": {
            "type": "number",
            "title": "Mtbf Hours"
          },
          "mttr_hours": {
            "type": "number",
            "title": "Mttr Hours"
          },
          "mission_time_hours": {
            "type": "number",
            "title": "Mission Time Hours"
          },
          "availability": {
            "type": "number",
            "title": "Availability"
          },
          "reliability": {
            "type": "number",
            "title": "Reliability"
          },
          "failure_rate_per_hour": {
            "type": "number",
            "title": "Failure Rate Per Hour"
          },
          "expected_failures": {
            "type": "number",
            "title": "Expected Failures"
          },
          "created_at": {
            "type": "string",
            "format": "date-time",
            "title": "Created At"
          }
        },
        "type": "object",
        "required": [
          "mtbf_hours",
          "mttr_hours",
          "mission_time_hours",
          "availability",
          "reliability",
          "failure_rate_per_hour",
          "expected_failures",
          "created_at"
        ],
        "title": "ReliabilityOutput"
      },
      "ReliabilityScoreComponent": {
        "properties": {
          "name": {
            "type": "string",
            "maxLength": 100,
            "minLength": 1,
            "title": "Name"
          },
          "value": {
            "type": "number",
            "maximum": 1.0,
            "minimum": 0.0,
            "title": "Value",
            "description": "Normalized component value between 0.0 and 1.0."
          },
          "weight": {
            "type": "number",
            "maximum": 1.0,
            "exclusiveMinimum": 0.0,
            "title": "Weight",
            "description": "Component weight; weights are normalized if they do not sum to 1.0."
          },
          "nist_function": {
            "anyOf": [
              {
                "$ref": "#/components/schemas/NISTFunction"
              },
              {
                "type": "null"
              }
            ],
            "description": "Optional NIST AI RMF function this component maps to."
          }
        },
        "type": "object",
        "required": [
          "name",
          "value",
          "weight"
        ],
        "title": "ReliabilityScoreComponent",
        "description": "One input signal to the weighted reliability score."
      },
      "ReliabilityScoreHistoryOut": {
        "properties": {
          "system_name": {
            "anyOf": [
              {
                "type": "string"
              },
              {
                "type": "null"
              }
            ],
            "title": "System Name",
            "description": "Filter applied (``None`` = all systems)."
          },
          "stats": {
            "$ref": "#/components/schemas/ScoreTrendStats"
          },
          "records": {
            "items": {
              "$ref": "#/components/schemas/ReliabilityScoreRecordOut"
            },
            "type": "array",
            "title": "Records"
          }
        },
        "type": "object",
        "required": [
          "stats",
          "records"
        ],
        "title": "ReliabilityScoreHistoryOut",
        "description": "Response body for GET /reliability/score/history."
      },
      "ReliabilityScoreInput": {
        "properties": {
          "system_name": {
            "type": "string",
            "maxLength": 200,
            "minLength": 1,
            "title": "System Name"
          },
          "components": {
            "items": {
              "$ref": "#/components/schemas/ReliabilityScoreComponent"
            },
            "type": "array",
            "minItems": 1,
            "title": "Components"
          }
        },
        "type": "object",
        "required": [
          "system_name",
          "components"
        ],
        "title": "ReliabilityScoreInput",
        "description": "Request body for POST /reliability/score."
      },
      "ReliabilityScoreOutput": {
        "properties": {
          "system_name": {
            "type": "string",
            "title": "System Name"
          },
          "composite_score": {
            "type": "number",
            "title": "Composite Score",
            "description": "Weighted composite score, 0-100."
          },
          "tier": {
            "type": "string",
            "title": "Tier",
            "description": "LOW (>=80), MEDIUM (>=60), or HIGH (<60)."
          },
          "weights_normalized": {
            "type": "boolean",
            "title": "Weights Normalized",
            "description": "True if input weights did not sum to 1.0 and were normalized."
          },
          "nist_breakdown": {
            "$ref": "#/components/schemas/NISTBreakdown"
          },
          "components": {
            "items": {
              "$ref": "#/components/schemas/ReliabilityScoreComponent"
            },
            "type": "array",
            "title": "Components"
          },
          "computed_at": {
            "type": "string",
            "format": "date-time",
            "title": "Computed At"
          }
        },
        "type": "object",
        "required": [
          "system_name",
          "composite_score",
          "tier",
          "weights_normalized",
          "nist_breakdown",
          "components",
          "computed_at"
        ],
        "title": "ReliabilityScoreOutput",
        "description": "Response body for POST /reliability/score."
      },
      "ReliabilityScoreRecordOut": {
        "properties": {
          "id": {
            "type": "integer",
            "title": "Id"
          },
          "system_name": {
            "type": "string",
            "title": "System Name"
          },
          "composite_score": {
            "type": "number",
            "title": "Composite Score"
          },
          "tier": {
            "type": "string",
            "title": "Tier"
          },
          "weights_normalized": {
            "type": "boolean",
            "title": "Weights Normalized"
          },
          "nist_govern": {
            "anyOf": [
              {
                "type": "number"
              },
              {
                "type": "null"
              }
            ],
            "title": "Nist Govern"
          },
          "nist_map": {
            "anyOf": [
              {
                "type": "number"
              },
              {
                "type": "null"
              }
            ],
            "title": "Nist Map"
          },
          "nist_measure": {
            "anyOf": [
              {
                "type": "number"
              },
              {
                "type": "null"
              }
            ],
            "title": "Nist Measure"
          },
          "nist_manage": {
            "anyOf": [
              {
                "type": "number"
              },
              {
                "type": "null"
              }
            ],
            "title": "Nist Manage"
          },
          "created_at": {
            "type": "string",
            "format": "date-time",
            "title": "Created At"
          }
        },
        "type": "object",
        "required": [
          "id",
          "system_name",
          "composite_score",
          "tier",
          "weights_normalized",
          "created_at"
        ],
        "title": "ReliabilityScoreRecordOut",
        "description": "One persisted reliability score row."
      },
      "ReliabilityScoreWithExplanation": {
        "properties": {
          "system_name": {
            "type": "string",
            "title": "System Name"
          },
          "composite_score": {
            "type": "number",
            "title": "Composite Score",
            "description": "Weighted composite score, 0-100."
          },
          "tier": {
            "type": "string",
            "title": "Tier",
            "description": "LOW (>=80), MEDIUM (>=60), or HIGH (<60)."
          },
          "weights_normalized": {
            "type": "boolean",
            "title": "Weights Normalized",
            "description": "True if input weights did not sum to 1.0 and were normalized."
          },
          "nist_breakdown": {
            "$ref": "#/components/schemas/NISTBreakdown"
          },
          "components": {
            "items": {
              "$ref": "#/components/schemas/ReliabilityScoreComponent"
            },
            "type": "array",
            "title": "Components"
          },
          "computed_at": {
            "type": "string",
            "format": "date-time",
            "title": "Computed At"
          },
          "explanation": {
            "$ref": "#/components/schemas/ScoreExplanation"
          }
        },
        "type": "object",
        "required": [
          "system_name",
          "composite_score",
          "tier",
          "weights_normalized",
          "nist_breakdown",
          "components",
          "computed_at",
          "explanation"
        ],
        "title": "ReliabilityScoreWithExplanation",
        "description": "Response body for POST /reliability/score/explain.\n\nExtends the base score response with a detailed ``explanation`` object\nthat tells the caller *why* the composite landed where it did and what\nto do about it."
      },
      "ScoreContribution": {
        "properties": {
          "component_name": {
            "type": "string",
            "title": "Component Name"
          },
          "value": {
            "type": "number",
            "title": "Value"
          },
          "weight": {
            "type": "number",
            "title": "Weight"
          },
          "contribution": {
            "type": "number",
            "title": "Contribution",
            "description": "Component's share of the composite score on a 0-100 scale (normalized weight * value * 100)."
          },
          "contribution_percent": {
            "type": "number",
            "title": "Contribution Percent",
            "description": "Percent of the composite score attributable to this component (sums to 100 across all components when composite > 0)."
          },
          "nist_function": {
            "anyOf": [
              {
                "$ref": "#/components/schemas/NISTFunction"
              },
              {
                "type": "null"
              }
            ]
          }
        },
        "type": "object",
        "required": [
          "component_name",
          "value",
          "weight",
          "contribution",
          "contribution_percent"
        ],
        "title": "ScoreContribution",
        "description": "One component's contribution to the composite score."
      },
      "ScoreExplanation": {
        "properties": {
          "top_driver": {
            "anyOf": [
              {
                "$ref": "#/components/schemas/ScoreContribution"
              },
              {
                "type": "null"
              }
            ],
            "description": "Component contributing most to the composite score."
          },
          "top_gap": {
            "anyOf": [
              {
                "$ref": "#/components/schemas/ScoreContribution"
              },
              {
                "type": "null"
              }
            ],
            "description": "Component with the lowest value (largest improvement opportunity)."
          },
          "contributions": {
            "items": {
              "$ref": "#/components/schemas/ScoreContribution"
            },
            "type": "array",
            "title": "Contributions",
            "description": "Per-component contributions, sorted highest first."
          },
          "tier_gap": {
            "$ref": "#/components/schemas/TierGap"
          },
          "weakest_nist_function": {
            "anyOf": [
              {
                "$ref": "#/components/schemas/NISTFunction"
              },
              {
                "type": "null"
              }
            ]
          },
          "strongest_nist_function": {
            "anyOf": [
              {
                "$ref": "#/components/schemas/NISTFunction"
              },
              {
                "type": "null"
              }
            ]
          },
          "recommendation": {
            "type": "string",
            "title": "Recommendation",
            "description": "One-sentence plain-English suggestion for the owner."
          }
        },
        "type": "object",
        "required": [
          "contributions",
          "tier_gap",
          "recommendation"
        ],
        "title": "ScoreExplanation",
        "description": "Human- and machine-readable rationale for a composite score."
      },
      "ScoreTrendStats": {
        "properties": {
          "count": {
            "type": "integer",
            "title": "Count"
          },
          "latest_score": {
            "anyOf": [
              {
                "type": "number"
              },
              {
                "type": "null"
              }
            ],
            "title": "Latest Score"
          },
          "latest_tier": {
            "anyOf": [
              {
                "type": "string"
              },
              {
                "type": "null"
              }
            ],
            "title": "Latest Tier"
          },
          "earliest_score": {
            "anyOf": [
              {
                "type": "number"
              },
              {
                "type": "null"
              }
            ],
            "title": "Earliest Score"
          },
          "earliest_tier": {
            "anyOf": [
              {
                "type": "string"
              },
              {
                "type": "null"
              }
            ],
            "title": "Earliest Tier"
          },
          "rolling_average": {
            "anyOf": [
              {
                "type": "number"
              },
              {
                "type": "null"
              }
            ],
            "title": "Rolling Average",
            "description": "Mean composite score across all returned records."
          },
          "min_score": {
            "anyOf": [
              {
                "type": "number"
              },
              {
                "type": "null"
              }
            ],
            "title": "Min Score"
          },
          "max_score": {
            "anyOf": [
              {
                "type": "number"
              },
              {
                "type": "null"
              }
            ],
            "title": "Max Score"
          },
          "trend_direction": {
            "type": "string",
            "title": "Trend Direction",
            "description": "'improving', 'degrading', 'stable', or 'insufficient_data'."
          },
          "tier_transitions": {
            "items": {
              "$ref": "#/components/schemas/TierTransition"
            },
            "type": "array",
            "title": "Tier Transitions"
          }
        },
        "type": "object",
        "required": [
          "count",
          "trend_direction"
        ],
        "title": "ScoreTrendStats",
        "description": "Aggregate statistics computed across a history window."
      },
      "SprintSummary": {
        "properties": {
          "current_sprint": {
            "type": "integer",
            "title": "Current Sprint"
          },
          "total_sprints": {
            "type": "integer",
            "title": "Total Sprints"
          },
          "release": {
            "type": "string",
            "title": "Release"
          },
          "branch": {
            "type": "string",
            "title": "Branch"
          }
        },
        "type": "object",
        "required": [
          "current_sprint",
          "total_sprints",
          "release",
          "branch"
        ],
        "title": "SprintSummary",
        "description": "High-level roadmap status for the frontend."
      },
      "TierGap": {
        "properties": {
          "current_tier": {
            "type": "string",
            "title": "Current Tier"
          },
          "next_tier_up": {
            "anyOf": [
              {
                "type": "string"
              },
              {
                "type": "null"
              }
            ],
            "title": "Next Tier Up",
            "description": "Tier label above the current one, or null if already at LOW."
          },
          "points_needed_up": {
            "anyOf": [
              {
                "type": "number"
              },
              {
                "type": "null"
              }
            ],
            "title": "Points Needed Up",
            "description": "Composite points needed to jump to the next tier up."
          },
          "next_tier_down": {
            "anyOf": [
              {
                "type": "string"
              },
              {
                "type": "null"
              }
            ],
            "title": "Next Tier Down",
            "description": "Tier label below the current one, or null if already at HIGH."
          },
          "points_buffer_down": {
            "anyOf": [
              {
                "type": "number"
              },
              {
                "type": "null"
              }
            ],
            "title": "Points Buffer Down",
            "description": "Composite points of headroom before falling to the next tier down."
          }
        },
        "type": "object",
        "required": [
          "current_tier"
        ],
        "title": "TierGap",
        "description": "How close the current composite is to adjacent tiers."
      },
      "TierTransition": {
        "properties": {
          "from_tier": {
            "type": "string",
            "title": "From Tier"
          },
          "to_tier": {
            "type": "string",
            "title": "To Tier"
          },
          "at": {
            "type": "string",
            "format": "date-time",
            "title": "At"
          },
          "composite_score": {
            "type": "number",
            "title": "Composite Score",
            "description": "Composite score at the moment of the transition."
          }
        },
        "type": "object",
        "required": [
          "from_tier",
          "to_tier",
          "at",
          "composite_score"
        ],
        "title": "TierTransition",
        "description": "One tier change detected in the history stream."
      },
      "TokenOut": {
        "properties": {
          "access_token": {
            "type": "string",
            "title": "Access Token"
          },
          "token_type": {
            "type": "string",
            "title": "Token Type",
            "default": "bearer"
          },
          "expires_in": {
            "type": "integer",
            "title": "Expires In"
          }
        },
        "type": "object",
        "required": [
          "access_token",
          "expires_in"
        ],
        "title": "TokenOut"
      },
      "UserLogin": {
        "properties": {
          "email": {
            "type": "string",
            "title": "Email"
          },
          "password": {
            "type": "string",
            "title": "Password"
          }
        },
        "type": "object",
        "required": [
          "email",
          "password"
        ],
        "title": "UserLogin"
      },
      "UserOut": {
        "properties": {
          "id": {
            "type": "integer",
            "title": "Id"
          },
          "email": {
            "type": "string",
            "title": "Email"
          },
          "role": {
            "type": "string",
            "title": "Role"
          },
          "created_at": {
            "type": "string",
            "format": "date-time",
            "title": "Created At"
          }
        },
        "type": "object",
        "required": [
          "id",
          "email",
          "role",
          "created_at"
        ],
        "title": "UserOut"
      },
      "UserRegister": {
        "properties": {
          "email": {
            "type": "string",
            "maxLength": 200,
            "minLength": 3,
            "title": "Email"
          },
          "password": {
            "type": "string",
            "maxLength": 200,
            "minLength": 8,
            "title": "Password"
          }
        },
        "type": "object",
        "required": [
          "email",
          "password"
        ],
        "title": "UserRegister"
      },
      "ValidationError": {
        "properties": {
          "loc": {
            "items": {
              "anyOf": [
                {
                  "type": "string"
                },
                {
                  "type": "integer"
                }
              ]
            },
            "type": "array",
            "title": "Location"
          },
          "msg": {
            "type": "string",
            "title": "Message"
          },
          "type": {
            "type": "string",
            "title": "Error Type"
          },
          "input": {
            "title": "Input"
          },
          "ctx": {
            "type": "object",
            "title": "Context"
          }
        },
        "type": "object",
        "required": [
          "loc",
          "msg",
          "type"
        ],
        "title": "ValidationError"
      }
    },
    "securitySchemes": {
      "OAuth2PasswordBearer": {
        "type": "oauth2",
        "flows": {
          "password": {
            "scopes": {},
            "tokenUrl": "/auth/login"
          }
        }
      }
    }
  }
}